flet_box/__init__.py
flet_box/flet_box.py
flet_box/assets/avatar.jpg
flet_box/assets/avatar.png
flet_box/assets/dragg_container.jpg
flet_box/assets/dragg_container3.jpg
flet_box/assets/image.jpg
flet_box/assets/img.jpg
flet_box/assets/logo.jpg
flet_box/assets/logo_mark.png
flet_box/assets/my_avatar.png
flet_box/assets/no_imagen.jpg
flet_box/assets/splash.jpg
flet_box/assets/wallpaper.jpg
flet_box/extra_utils/__init__.py
flet_box/extra_utils/about/__init__.py
flet_box/extra_utils/about/about.py
flet_box/extra_utils/alert/__init__.py
flet_box/extra_utils/alert/alert_selected.py
flet_box/extra_utils/chat_gpt_browser/__init__.py
flet_box/extra_utils/chat_gpt_browser/gpt_browser.py
flet_box/extra_utils/chat_gpt_browser/library_chatgpt.py
flet_box/extra_utils/color_browser/__init__.py
flet_box/extra_utils/color_browser/color_browser.py
flet_box/extra_utils/config_container/__init__.py
flet_box/extra_utils/config_container/blur_color_entry.py
flet_box/extra_utils/config_container/bool_entry.py
flet_box/extra_utils/config_container/color_entry.py
flet_box/extra_utils/config_container/double_entry.py
flet_box/extra_utils/config_container/four_entry.py
flet_box/extra_utils/config_container/gradient_entry.py
flet_box/extra_utils/config_container/selection_entry.py
flet_box/extra_utils/config_container/single_entry.py
flet_box/extra_utils/config_container/widget_editor.py
flet_box/extra_utils/drag_container/__init__.py
flet_box/extra_utils/drag_container/dragg_widget.py
flet_box/extra_utils/drag_container/infinity_box_layer_one.py
flet_box/extra_utils/drag_container/widget_drag_editor.py
flet_box/extra_utils/icon_browser/__init__.py
flet_box/extra_utils/icon_browser/icon_browser.py
flet_box/extra_utils/lite_menu_bar_down_phone/__init__.py
flet_box/extra_utils/lite_menu_bar_down_phone/footer_bar_menu_phone.py
flet_box/extra_utils/lite_menu_bar_down_phone/selected_widget.py
flet_box/extra_utils/lite_menu_bar_right_phone/__init__.py
flet_box_gui-0.1.2.2.dist-info/LICENSE
flet_box_gui-0.1.2.2.dist-info/METADATA
flet_box_gui-0.1.2.2.dist-info/WHEEL
flet_box_gui-0.1.2.2.dist-info/entry_points.txt
flet_box_gui-0.1.2.2.dist-info/top_level.txt
flet_box_gui-0.1.2.2.dist-info/RECORD
